.gitignore
.pylintrc
.readthedocs.yml
.travis.yml
CODE_OF_CONDUCT.md
LICENSE
README.rst
adafruit_lsm303.py
requirements.txt
setup.py
adafruit_circuitpython_lsm303.egg-info/PKG-INFO
adafruit_circuitpython_lsm303.egg-info/SOURCES.txt
adafruit_circuitpython_lsm303.egg-info/dependency_links.txt
adafruit_circuitpython_lsm303.egg-info/requires.txt
adafruit_circuitpython_lsm303.egg-info/top_level.txt
docs/api.rst
docs/conf.py
docs/examples.rst
docs/index.rst
docs/_static/favicon.ico
examples/lsm303_fast_accel.py
examples/lsm303_fast_mag.py
examples/lsm303_raw_and_cooked.py
examples/lsm303_simpletest.py